timeseries_performance_calculator/__init__.py
timeseries_performance_calculator/consts.py
timeseries_performance_calculator/basis/__init__.py
timeseries_performance_calculator/basis/annualized_return_calculator.py
timeseries_performance_calculator/basis/annualized_volatility_calculator.py
timeseries_performance_calculator/basis/basis.py
timeseries_performance_calculator/basis/beta_calculator.py
timeseries_performance_calculator/basis/down_capture.py
timeseries_performance_calculator/basis/information_ratio_calculator.py
timeseries_performance_calculator/basis/maxdrawdown_calculator.py
timeseries_performance_calculator/basis/return_calculator.py
timeseries_performance_calculator/basis/sharpe_ratio_calculator.py
timeseries_performance_calculator/basis/sortino_ratio_calculator.py
timeseries_performance_calculator/basis/tracking_error_calculator.py
timeseries_performance_calculator/basis/up_capture.py
timeseries_performance_calculator/basis/updown_capture_ratio.py
timeseries_performance_calculator/basis/winning_ratio_calculator.py
timeseries_performance_calculator/classes/__init__.py
timeseries_performance_calculator/classes/basis.py
timeseries_performance_calculator/classes/crosssection.py
timeseries_performance_calculator/classes/performance.py
timeseries_performance_calculator/classes/seasonality.py
timeseries_performance_calculator/crosssectional_analysis/__init__.py
timeseries_performance_calculator/crosssectional_analysis/basis.py
timeseries_performance_calculator/crosssectional_analysis/parser.py
timeseries_performance_calculator/crosssectional_analysis/utils.py
timeseries_performance_calculator/functionals/__init__.py
timeseries_performance_calculator/functionals/basis.py
timeseries_performance_calculator/functionals/maps.py
timeseries_performance_calculator/functionals/utils.py
timeseries_performance_calculator/matrix/__init__.py
timeseries_performance_calculator/matrix/winning_ratio.py
timeseries_performance_calculator/tables/__init__.py
timeseries_performance_calculator-0.3.11.dist-info/METADATA
timeseries_performance_calculator-0.3.11.dist-info/WHEEL
timeseries_performance_calculator-0.3.11.dist-info/top_level.txt
timeseries_performance_calculator-0.3.11.dist-info/RECORD
