Metadata-Version: 2.4
Name: timeseries_performance_calculator
Version: 0.3.11
Summary: A Python package for calculating and analyzing time series performance metrics
Author: June Young Park
Author-email: juneyoungpaak@gmail.com
Classifier: Programming Language :: Python :: 3
Classifier: Programming Language :: Python :: 3.7
Classifier: Programming Language :: Python :: 3.8
Classifier: Programming Language :: Python :: 3.9
Classifier: Programming Language :: Python :: 3.10
Classifier: Topic :: Scientific/Engineering :: Mathematics
Classifier: Topic :: Office/Business :: Financial
Classifier: Intended Audience :: Financial and Insurance Industry
Classifier: Intended Audience :: Science/Research
Requires-Python: >=3.7
Requires-Dist: universal_timeseries_transformer>=0.3.7
Requires-Dist: string_date_controller>=0.3.0
Requires-Dist: canonical_transformer>=1.0.5
Dynamic: author
Dynamic: author-email
Dynamic: classifier
Dynamic: description
Dynamic: description-content-type
Dynamic: requires-dist
Dynamic: requires-python
Dynamic: summary
